mimimon/__init__.py
mimimon/__main__.py
mimimon/cli/__init__.py
mimimon/cli/main.py
mimimon/client/__init__.py
mimimon/client/client.py
mimimon/client/enhanced_client.py
mimimon/mcp/__init__.py
mimimon/mcp/__main__.py
mimimon/mcp/client.py
mimimon/monitoring/__init__.py
mimimon/monitoring/claude_wrapper.py
mimimon/monitoring/file_watcher.py
mimimon/monitoring/log_parser.py
mimimon/monitoring/session_tracker.py
mimimon/monitoring/terminal_monitor.py
mimimon/server/__init__.py
mimimon/server/__main__.py
mimimon/server/app.py
mimimon/server/auth.py
mimimon/server/config.py
mimimon/server/database.py
mimimon/server/demo_auth.py
mimimon/server/main.py
mimimon/server/realtime.py
mimimon/server/routers/__init__.py
mimimon/server/routers/agents.py
mimimon/server/routers/auth.py
mimimon/server/routers/messages.py
mimimon/server/routers/sessions.py
mimimon-0.1.0.dist-info/METADATA
mimimon-0.1.0.dist-info/WHEEL
mimimon-0.1.0.dist-info/entry_points.txt
mimimon-0.1.0.dist-info/top_level.txt
mimimon-0.1.0.dist-info/RECORD
