Metadata-Version: 2.4
Name: mimimon
Version: 0.1.0
Summary: MiMiMON - AI Agent Monitoring and Communication Platform
Author-email: MiMiMON Team <team@mimimon.ai>
License-Expression: MIT
Project-URL: Homepage, https://mimimon.ai
Project-URL: Documentation, https://docs.mimimon.ai
Project-URL: Repository, https://github.com/mimimon-ai/mimimon
Project-URL: Issues, https://github.com/mimimon-ai/mimimon/issues
Project-URL: Mobile App, https://apps.apple.com/app/mimimon
Project-URL: Web Dashboard, https://dashboard.mimimon.ai
Keywords: AI,agents,CLI,monitoring,MCP,communication
Classifier: Development Status :: 3 - Alpha
Classifier: Intended Audience :: Developers
Classifier: Programming Language :: Python :: 3
Classifier: Programming Language :: Python :: 3.8
Classifier: Programming Language :: Python :: 3.9
Classifier: Programming Language :: Python :: 3.10
Classifier: Programming Language :: Python :: 3.11
Classifier: Programming Language :: Python :: 3.12
Classifier: Topic :: Software Development :: Libraries :: Python Modules
Classifier: Topic :: System :: Monitoring
Requires-Python: >=3.8
Requires-Dist: typer>=0.9.0
Requires-Dist: rich>=13.0.0
Requires-Dist: pydantic>=2.0.0
Requires-Dist: requests>=2.28.0
Requires-Dist: websockets>=11.0.0
Requires-Dist: httpx>=0.24.0
Requires-Dist: psutil>=5.9.0
Requires-Dist: fastapi>=0.100.0
Requires-Dist: uvicorn>=0.20.0
Requires-Dist: watchdog>=3.0.0
Provides-Extra: dev
Requires-Dist: pytest>=7.0.0; extra == "dev"
Requires-Dist: black>=23.0.0; extra == "dev"
Requires-Dist: ruff>=0.1.0; extra == "dev"
Requires-Dist: mypy>=1.0.0; extra == "dev"
Requires-Dist: pre-commit>=3.0.0; extra == "dev"
